{
  "id": "2e3201cf-bb11-4d8f-8023-e0918e877c98",
  "prevId": "97736c77-2514-41e6-b3ba-0f1dc38e3f07",
  "version": "5",
  "dialect": "pg",
  "tables": {
    "attempt_answers": {
      "name": "attempt_answers",
      "schema": "",
      "columns": {
        "id": {
          "name": "id",
          "type": "serial",
          "primaryKey": true,
          "notNull": true
        },
        "attempt_id": {
          "name": "attempt_id",
          "type": "integer",
          "primaryKey": false,
          "notNull": true
        },
        "question_id": {
          "name": "question_id",
          "type": "integer",
          "primaryKey": false,
          "notNull": true
        },
        "selected_option_id": {
          "name": "selected_option_id",
          "type": "integer",
          "primaryKey": false,
          "notNull": false
        },
        "answer_text": {
          "name": "answer_text",
          "type": "text",
          "primaryKey": false,
          "notNull": false
        },
        "is_correct": {
          "name": "is_correct",
          "type": "boolean",
          "primaryKey": false,
          "notNull": false
        },
        "points_awarded": {
          "name": "points_awarded",
          "type": "integer",
          "primaryKey": false,
          "notNull": false,
          "default": 0
        }
      },
      "indexes": {},
      "foreignKeys": {
        "attempt_answers_attempt_id_test_attempts_id_fk": {
          "name": "attempt_answers_attempt_id_test_attempts_id_fk",
          "tableFrom": "attempt_answers",
          "tableTo": "test_attempts",
          "columnsFrom": [
            "attempt_id"
          ],
          "columnsTo": [
            "id"
          ],
          "onDelete": "cascade",
          "onUpdate": "no action"
        },
        "attempt_answers_question_id_questions_id_fk": {
          "name": "attempt_answers_question_id_questions_id_fk",
          "tableFrom": "attempt_answers",
          "tableTo": "questions",
          "columnsFrom": [
            "question_id"
          ],
          "columnsTo": [
            "id"
          ],
          "onDelete": "no action",
          "onUpdate": "no action"
        },
        "attempt_answers_selected_option_id_question_options_id_fk": {
          "name": "attempt_answers_selected_option_id_question_options_id_fk",
          "tableFrom": "attempt_answers",
          "tableTo": "question_options",
          "columnsFrom": [
            "selected_option_id"
          ],
          "columnsTo": [
            "id"
          ],
          "onDelete": "no action",
          "onUpdate": "no action"
        }
      },
      "compositePrimaryKeys": {},
      "uniqueConstraints": {}
    },
    "question_banks": {
      "name": "question_banks",
      "schema": "",
      "columns": {
        "id": {
          "name": "id",
          "type": "serial",
          "primaryKey": true,
          "notNull": true
        },
        "name": {
          "name": "name",
          "type": "text",
          "primaryKey": false,
          "notNull": true
        },
        "description": {
          "name": "description",
          "type": "text",
          "primaryKey": false,
          "notNull": false
        },
        "created_by": {
          "name": "created_by",
          "type": "integer",
          "primaryKey": false,
          "notNull": true
        },
        "created_at": {
          "name": "created_at",
          "type": "timestamp",
          "primaryKey": false,
          "notNull": false,
          "default": "now()"
        }
      },
      "indexes": {},
      "foreignKeys": {
        "question_banks_created_by_users_id_fk": {
          "name": "question_banks_created_by_users_id_fk",
          "tableFrom": "question_banks",
          "tableTo": "users",
          "columnsFrom": [
            "created_by"
          ],
          "columnsTo": [
            "id"
          ],
          "onDelete": "no action",
          "onUpdate": "no action"
        }
      },
      "compositePrimaryKeys": {},
      "uniqueConstraints": {}
    },
    "question_options": {
      "name": "question_options",
      "schema": "",
      "columns": {
        "id": {
          "name": "id",
          "type": "serial",
          "primaryKey": true,
          "notNull": true
        },
        "question_id": {
          "name": "question_id",
          "type": "integer",
          "primaryKey": false,
          "notNull": true
        },
        "text": {
          "name": "text",
          "type": "text",
          "primaryKey": false,
          "notNull": true
        },
        "is_correct": {
          "name": "is_correct",
          "type": "boolean",
          "primaryKey": false,
          "notNull": false,
          "default": false
        }
      },
      "indexes": {},
      "foreignKeys": {
        "question_options_question_id_questions_id_fk": {
          "name": "question_options_question_id_questions_id_fk",
          "tableFrom": "question_options",
          "tableTo": "questions",
          "columnsFrom": [
            "question_id"
          ],
          "columnsTo": [
            "id"
          ],
          "onDelete": "cascade",
          "onUpdate": "no action"
        }
      },
      "compositePrimaryKeys": {},
      "uniqueConstraints": {}
    },
    "questions": {
      "name": "questions",
      "schema": "",
      "columns": {
        "id": {
          "name": "id",
          "type": "serial",
          "primaryKey": true,
          "notNull": true
        },
        "bank_id": {
          "name": "bank_id",
          "type": "integer",
          "primaryKey": false,
          "notNull": false
        },
        "type": {
          "name": "type",
          "type": "question_type",
          "primaryKey": false,
          "notNull": true
        },
        "text": {
          "name": "text",
          "type": "text",
          "primaryKey": false,
          "notNull": true
        },
        "points": {
          "name": "points",
          "type": "integer",
          "primaryKey": false,
          "notNull": false,
          "default": 1
        },
        "created_by": {
          "name": "created_by",
          "type": "integer",
          "primaryKey": false,
          "notNull": true
        },
        "created_at": {
          "name": "created_at",
          "type": "timestamp",
          "primaryKey": false,
          "notNull": false,
          "default": "now()"
        }
      },
      "indexes": {},
      "foreignKeys": {
        "questions_bank_id_question_banks_id_fk": {
          "name": "questions_bank_id_question_banks_id_fk",
          "tableFrom": "questions",
          "tableTo": "question_banks",
          "columnsFrom": [
            "bank_id"
          ],
          "columnsTo": [
            "id"
          ],
          "onDelete": "cascade",
          "onUpdate": "no action"
        },
        "questions_created_by_users_id_fk": {
          "name": "questions_created_by_users_id_fk",
          "tableFrom": "questions",
          "tableTo": "users",
          "columnsFrom": [
            "created_by"
          ],
          "columnsTo": [
            "id"
          ],
          "onDelete": "no action",
          "onUpdate": "no action"
        }
      },
      "compositePrimaryKeys": {},
      "uniqueConstraints": {}
    },
    "test_attempts": {
      "name": "test_attempts",
      "schema": "",
      "columns": {
        "id": {
          "name": "id",
          "type": "serial",
          "primaryKey": true,
          "notNull": true
        },
        "test_id": {
          "name": "test_id",
          "type": "integer",
          "primaryKey": false,
          "notNull": true
        },
        "student_id": {
          "name": "student_id",
          "type": "integer",
          "primaryKey": false,
          "notNull": true
        },
        "status": {
          "name": "status",
          "type": "attempt_status",
          "primaryKey": false,
          "notNull": false,
          "default": "'in_progress'"
        },
        "score": {
          "name": "score",
          "type": "integer",
          "primaryKey": false,
          "notNull": false
        },
        "total_points": {
          "name": "total_points",
          "type": "integer",
          "primaryKey": false,
          "notNull": false
        },
        "is_passed": {
          "name": "is_passed",
          "type": "boolean",
          "primaryKey": false,
          "notNull": false
        },
        "is_flagged": {
          "name": "is_flagged",
          "type": "boolean",
          "primaryKey": false,
          "notNull": false,
          "default": false
        },
        "flag_reason": {
          "name": "flag_reason",
          "type": "text",
          "primaryKey": false,
          "notNull": false
        },
        "started_at": {
          "name": "started_at",
          "type": "timestamp",
          "primaryKey": false,
          "notNull": false,
          "default": "now()"
        },
        "submitted_at": {
          "name": "submitted_at",
          "type": "timestamp",
          "primaryKey": false,
          "notNull": false
        }
      },
      "indexes": {},
      "foreignKeys": {
        "test_attempts_test_id_tests_id_fk": {
          "name": "test_attempts_test_id_tests_id_fk",
          "tableFrom": "test_attempts",
          "tableTo": "tests",
          "columnsFrom": [
            "test_id"
          ],
          "columnsTo": [
            "id"
          ],
          "onDelete": "cascade",
          "onUpdate": "no action"
        },
        "test_attempts_student_id_users_id_fk": {
          "name": "test_attempts_student_id_users_id_fk",
          "tableFrom": "test_attempts",
          "tableTo": "users",
          "columnsFrom": [
            "student_id"
          ],
          "columnsTo": [
            "id"
          ],
          "onDelete": "cascade",
          "onUpdate": "no action"
        }
      },
      "compositePrimaryKeys": {},
      "uniqueConstraints": {}
    },
    "test_questions": {
      "name": "test_questions",
      "schema": "",
      "columns": {
        "id": {
          "name": "id",
          "type": "serial",
          "primaryKey": true,
          "notNull": true
        },
        "test_id": {
          "name": "test_id",
          "type": "integer",
          "primaryKey": false,
          "notNull": true
        },
        "question_id": {
          "name": "question_id",
          "type": "integer",
          "primaryKey": false,
          "notNull": true
        },
        "order": {
          "name": "order",
          "type": "integer",
          "primaryKey": false,
          "notNull": true
        }
      },
      "indexes": {},
      "foreignKeys": {
        "test_questions_test_id_tests_id_fk": {
          "name": "test_questions_test_id_tests_id_fk",
          "tableFrom": "test_questions",
          "tableTo": "tests",
          "columnsFrom": [
            "test_id"
          ],
          "columnsTo": [
            "id"
          ],
          "onDelete": "cascade",
          "onUpdate": "no action"
        },
        "test_questions_question_id_questions_id_fk": {
          "name": "test_questions_question_id_questions_id_fk",
          "tableFrom": "test_questions",
          "tableTo": "questions",
          "columnsFrom": [
            "question_id"
          ],
          "columnsTo": [
            "id"
          ],
          "onDelete": "cascade",
          "onUpdate": "no action"
        }
      },
      "compositePrimaryKeys": {},
      "uniqueConstraints": {}
    },
    "tests": {
      "name": "tests",
      "schema": "",
      "columns": {
        "id": {
          "name": "id",
          "type": "serial",
          "primaryKey": true,
          "notNull": true
        },
        "title": {
          "name": "title",
          "type": "text",
          "primaryKey": false,
          "notNull": true
        },
        "description": {
          "name": "description",
          "type": "text",
          "primaryKey": false,
          "notNull": false
        },
        "created_by": {
          "name": "created_by",
          "type": "integer",
          "primaryKey": false,
          "notNull": true
        },
        "time_limit": {
          "name": "time_limit",
          "type": "integer",
          "primaryKey": false,
          "notNull": false
        },
        "max_attempts": {
          "name": "max_attempts",
          "type": "integer",
          "primaryKey": false,
          "notNull": false,
          "default": 1
        },
        "pass_mark_percent": {
          "name": "pass_mark_percent",
          "type": "integer",
          "primaryKey": false,
          "notNull": false,
          "default": 50
        },
        "start_date": {
          "name": "start_date",
          "type": "timestamp",
          "primaryKey": false,
          "notNull": false
        },
        "end_date": {
          "name": "end_date",
          "type": "timestamp",
          "primaryKey": false,
          "notNull": false
        },
        "status": {
          "name": "status",
          "type": "test_status",
          "primaryKey": false,
          "notNull": false,
          "default": "'draft'"
        },
        "created_at": {
          "name": "created_at",
          "type": "timestamp",
          "primaryKey": false,
          "notNull": false,
          "default": "now()"
        },
        "updated_at": {
          "name": "updated_at",
          "type": "timestamp",
          "primaryKey": false,
          "notNull": false,
          "default": "now()"
        }
      },
      "indexes": {},
      "foreignKeys": {
        "tests_created_by_users_id_fk": {
          "name": "tests_created_by_users_id_fk",
          "tableFrom": "tests",
          "tableTo": "users",
          "columnsFrom": [
            "created_by"
          ],
          "columnsTo": [
            "id"
          ],
          "onDelete": "no action",
          "onUpdate": "no action"
        }
      },
      "compositePrimaryKeys": {},
      "uniqueConstraints": {}
    },
    "users": {
      "name": "users",
      "schema": "",
      "columns": {
        "id": {
          "name": "id",
          "type": "serial",
          "primaryKey": true,
          "notNull": true
        },
        "name": {
          "name": "name",
          "type": "text",
          "primaryKey": false,
          "notNull": true
        },
        "email": {
          "name": "email",
          "type": "text",
          "primaryKey": false,
          "notNull": true
        },
        "password": {
          "name": "password",
          "type": "text",
          "primaryKey": false,
          "notNull": true
        },
        "role": {
          "name": "role",
          "type": "text",
          "primaryKey": false,
          "notNull": true
        },
        "created_at": {
          "name": "created_at",
          "type": "timestamp",
          "primaryKey": false,
          "notNull": false,
          "default": "now()"
        }
      },
      "indexes": {},
      "foreignKeys": {},
      "compositePrimaryKeys": {},
      "uniqueConstraints": {
        "users_email_unique": {
          "name": "users_email_unique",
          "nullsNotDistinct": false,
          "columns": [
            "email"
          ]
        }
      }
    }
  },
  "enums": {
    "attempt_status": {
      "name": "attempt_status",
      "values": {
        "in_progress": "in_progress",
        "submitted": "submitted"
      }
    },
    "question_type": {
      "name": "question_type",
      "values": {
        "multiple_choice": "multiple_choice",
        "true_false": "true_false",
        "short_answer": "short_answer"
      }
    },
    "test_status": {
      "name": "test_status",
      "values": {
        "draft": "draft",
        "published": "published",
        "archived": "archived"
      }
    }
  },
  "schemas": {},
  "_meta": {
    "columns": {},
    "schemas": {},
    "tables": {}
  }
}